sklearn_pmml_model/__init__.py
sklearn_pmml_model/datatypes.py
sklearn_pmml_model/base.py
sklearn_pmml_model/tree/_utils.pyx
sklearn_pmml_model/tree/_tree.pxd
sklearn_pmml_model/tree/tree.py
sklearn_pmml_model/tree/_splitter.cpython-39-darwin.so
sklearn_pmml_model/tree/quad_tree.pyx
sklearn_pmml_model/tree/_criterion.pyx
sklearn_pmml_model/tree/_splitter.pyx
sklearn_pmml_model/tree/__init__.py
sklearn_pmml_model/tree/quad_tree.cpython-39-darwin.so
sklearn_pmml_model/tree/_splitter.pxd
sklearn_pmml_model/tree/_tree.cpython-39-darwin.so
sklearn_pmml_model/tree/_criterion.pxd
sklearn_pmml_model/tree/quad_tree.pxd
sklearn_pmml_model/tree/_utils.cpython-39-darwin.so
sklearn_pmml_model/tree/_criterion.cpython-39-darwin.so
sklearn_pmml_model/tree/_utils.pxd
sklearn_pmml_model/tree/_tree.pyx
sklearn_pmml_model/ensemble/gb.py
sklearn_pmml_model/ensemble/__init__.py
sklearn_pmml_model/ensemble/_gradient_boosting.cpython-39-darwin.so
sklearn_pmml_model/ensemble/_gradient_boosting.pyx
sklearn_pmml_model/ensemble/forest.py
sklearn_pmml_model/linear_model/__init__.py
sklearn_pmml_model/linear_model/implementations.py
sklearn_pmml_model/linear_model/base.py
sklearn_pmml_model/neural_network/_base.py
sklearn_pmml_model/neural_network/__init__.py
sklearn_pmml_model/neural_network/_classes.py
sklearn_pmml_model/svm/_base.py
sklearn_pmml_model/svm/__init__.py
sklearn_pmml_model/svm/_classes.py
sklearn_pmml_model/auto_detect/__init__.py
sklearn_pmml_model/auto_detect/base.py
sklearn_pmml_model/naive_bayes/__init__.py
sklearn_pmml_model/naive_bayes/implementations.py
sklearn_pmml_model/neighbors/_base.py
sklearn_pmml_model/neighbors/__init__.py
sklearn_pmml_model/neighbors/_classes.py
tests/test_datatypes.py
tests/__init__.py
tests/test_base.py
sklearn_pmml_model-1.0.7.dist-info/RECORD
sklearn_pmml_model-1.0.7.dist-info/LICENSE
sklearn_pmml_model-1.0.7.dist-info/WHEEL
sklearn_pmml_model-1.0.7.dist-info/top_level.txt
sklearn_pmml_model-1.0.7.dist-info/METADATA
