Metadata-Version: 2.1
Name: sklearn-pmml-model
Version: 1.0.7
Summary: A library to parse PMML models into Scikit-learn estimators.
Home-page: https://github.com/iamDecode/sklearn-pmml-model
Author: Dennis Collaris
Author-email: d.collaris@me.com
License: BSD-2-Clause
Platform: UNKNOWN
Classifier: Programming Language :: Python :: 3
Classifier: License :: OSI Approved :: BSD License
Classifier: Operating System :: OS Independent
Classifier: Intended Audience :: Developers
Classifier: Intended Audience :: Science/Research
Classifier: Topic :: Software Development
Classifier: Topic :: Scientific/Engineering
License-File: LICENSE
Requires-Dist: numpy (>=1.16.0)
Requires-Dist: pandas
Requires-Dist: scipy
Requires-Dist: scikit-learn
Requires-Dist: cached-property
